puan/__init__.py
puan/npufunc.cpython-39-darwin.so
puan/logic/__init__.py
puan/logic/plog/__init__.py
puan/misc/__init__.py
puan/modules/__init__.py
puan/modules/configurator/__init__.py
puan/ndarray/__init__.py
puan/ndarray/npufunc.c
puan-0.5.0.dist-info/LICENSE
puan-0.5.0.dist-info/METADATA
puan-0.5.0.dist-info/WHEEL
puan-0.5.0.dist-info/top_level.txt
puan-0.5.0.dist-info/RECORD
