Metadata-Version: 2.1
Name: puan
Version: 0.5.0
Summary: Tools for combinatorial optimization
Author-email: Our Studio Void AB <moa@ourstudio.se>
Keywords: combinatorial optimization,milp,mllp,ilp,linear-programming,optimization
Classifier: Programming Language :: Python :: 3
Classifier: Operating System :: OS Independent
Requires-Python: >=3.8
License-File: LICENSE
